hydrology/__init__.py
hydrology/dataframe_api.py
hydrology/flooding.py
hydrology/hydrology.py
hydrology/models.py
hydrology/utils.py
hydrology-4.0.2.dist-info/LICENCE
hydrology-4.0.2.dist-info/METADATA
hydrology-4.0.2.dist-info/WHEEL
hydrology-4.0.2.dist-info/RECORD
