Metadata-Version: 2.1
Name: hydrology
Version: 4.0.2
Summary: Load data from the UK Hydology API
License: LICENCE
Keywords: Hydology,API,UK,Water,Data,Environment Agency,River,Flood,Rain,Weather
Author: Edward Jex
Author-email: edwardjex@live.co.uk
Requires-Python: >=3.11,<4.0
Classifier: License :: OSI Approved :: MIT License
Classifier: License :: Other/Proprietary License
Classifier: Programming Language :: Python
Classifier: Programming Language :: Python :: 3
Classifier: Programming Language :: Python :: 3.11
Classifier: Programming Language :: Python :: 3.12
Requires-Dist: httpx (>=0.27.0,<0.28.0)
Requires-Dist: polars[timezone] (>=1.2.1,<2.0.0)
